cycurl/__init__.py
cycurl/__version__.py
cycurl/_asyncio_selector.pxi
cycurl/_curl.c
cycurl/_curl.cp38-win_amd64.pyd
cycurl/_curl.pyi
cycurl/_curl.pyx
cycurl/consts.pxi
cycurl/curl.pxd
cycurl/libcurl.dll
cycurl/utils.pxi
cycurl/zlib.dll
cycurl/requests/__init__.py
cycurl/requests/cookies.py
cycurl/requests/errors.py
cycurl/requests/exceptions.py
cycurl/requests/headers.py
cycurl/requests/impersonate.py
cycurl/requests/models.py
cycurl/requests/session.py
cycurl/requests/utils.py
cycurl/requests/websockets.py
cycurl-0.11.4.dist-info/LICENSE
cycurl-0.11.4.dist-info/METADATA
cycurl-0.11.4.dist-info/WHEEL
cycurl-0.11.4.dist-info/top_level.txt
cycurl-0.11.4.dist-info/RECORD
