Metadata-Version: 2.1
Name: cycurl
Version: 0.11.4
Summary: Ultra fast python binding for curl-impersonate via cython, with impersonation support.
Home-page: https://github.com/synodriver/cycurl
Author: synodriver
Author-email: Lyonnet <infinitesheldon@gmail.com>
License: MIT License
Project-URL: repository, https://github.com/synodriver/cycurl
Classifier: Development Status :: 4 - Beta
Classifier: Intended Audience :: Developers
Classifier: Programming Language :: Python :: 3
Classifier: Programming Language :: Python :: 3.9
Classifier: Programming Language :: Python :: 3.10
Classifier: Programming Language :: Python :: 3.11
Classifier: Programming Language :: Python :: 3.12
Classifier: Programming Language :: Python :: 3.13
Requires-Python: >=3.6
License-File: LICENSE
Requires-Dist: cython>=3.0.9
Requires-Dist: certifi>=2024.2.2
Provides-Extra: build
Requires-Dist: cibuildwheel; extra == "build"
Requires-Dist: wheel; extra == "build"
Provides-Extra: dev
Requires-Dist: charset-normalizer<4.0,>=3.3.2; extra == "dev"
Requires-Dist: coverage<7.0,>=6.4.1; extra == "dev"
Requires-Dist: cryptography<43.0,>=42.0.5; extra == "dev"
Requires-Dist: httpx==0.23.1; extra == "dev"
Requires-Dist: mypy<2.0,>=1.9.0; extra == "dev"
Requires-Dist: pytest<9.0,>=8.1.1; extra == "dev"
Requires-Dist: pytest-asyncio<1.0,>=0.23.6; extra == "dev"
Requires-Dist: pytest-trio<1.0,>=0.8.0; extra == "dev"
Requires-Dist: ruff<1.0,>=0.3.5; extra == "dev"
Requires-Dist: trio<1.0,>=0.25.0; extra == "dev"
Requires-Dist: trustme<2.0,>=1.1.0; extra == "dev"
Requires-Dist: uvicorn<1.0,>=0.29.0; extra == "dev"
Requires-Dist: websockets<13.0,>=12.0; extra == "dev"
Requires-Dist: typing-extensions; extra == "dev"
Provides-Extra: extra
Requires-Dist: readability-lxml>=0.8.1; extra == "extra"
Requires-Dist: markdownify>=1.1.0; extra == "extra"
Requires-Dist: lxml-html-clean; extra == "extra"
Provides-Extra: test
Requires-Dist: charset-normalizer<4.0,>=3.3.2; extra == "test"
Requires-Dist: cryptography<43.0,>=42.0.5; extra == "test"
Requires-Dist: fastapi<1.0,==0.110.0; extra == "test"
Requires-Dist: httpx==0.23.1; extra == "test"
Requires-Dist: proxy.py<3.0,>=2.4.3; extra == "test"
Requires-Dist: pytest<9.0,>=8.1.1; extra == "test"
Requires-Dist: pytest-asyncio<1.0,>=0.23.6; extra == "test"
Requires-Dist: pytest-trio<1.0,>=0.8.0; extra == "test"
Requires-Dist: python-multipart<1.0,>=0.0.9; extra == "test"
Requires-Dist: trio<1.0,>=0.25.0; extra == "test"
Requires-Dist: trustme<2.0,>=1.1.0; extra == "test"
Requires-Dist: uvicorn<1.0,>=0.29.0; extra == "test"
Requires-Dist: websockets<13.0,>=12.0; extra == "test"
Requires-Dist: typing-extensions; extra == "test"
